pyshadoz/__init__.py
pyshadoz-0.1.3.dist-info/DESCRIPTION.rst
pyshadoz-0.1.3.dist-info/METADATA
pyshadoz-0.1.3.dist-info/RECORD
pyshadoz-0.1.3.dist-info/WHEEL
pyshadoz-0.1.3.dist-info/entry_points.txt
pyshadoz-0.1.3.dist-info/metadata.json
pyshadoz-0.1.3.dist-info/top_level.txt
