Metadata-Version: 2.0
Name: pyshadoz
Version: 0.1.3
Summary: pyshadoz is a pure Python package to read and write NASA Southern Hemisphere ADditional OZonesondes (SHADOZ) data.
Home-page: https://github.com/WMO-ET-WDC/pyshadoz
Author: Meteorological Service of Canada
Author-email: tom.kralidis@canada.ca
License: MIT
Keywords: shadoz Southern Hemisphere ADditional OZonesondes ozonesonde tropics subtropics nasa wmo
Platform: all
Classifier: Development Status :: 4 - Beta
Classifier: Environment :: Console
Classifier: Intended Audience :: Developers
Classifier: Intended Audience :: Science/Research
Classifier: License :: OSI Approved :: MIT License
Classifier: Operating System :: OS Independent
Classifier: Programming Language :: Python
Requires-Dist: click
Requires-Dist: six
